.coveragerc
.pylintrc
MANIFEST.in
README.rst
setup.cfg
setup.py
tox.ini
sphinxdocs/CHANGES.rst
sphinxdocs/README.rst
sphinxdocs/conf.py
sphinxdocs/index.rst
sphinxdocs/requirements.txt
sphinxdocs/robotdocs.rst
sphinxdocs/_static/empty.txt
src/crl/__init__.py
src/crl.examplelib.egg-info/PKG-INFO
src/crl.examplelib.egg-info/SOURCES.txt
src/crl.examplelib.egg-info/dependency_links.txt
src/crl.examplelib.egg-info/entry_points.txt
src/crl.examplelib.egg-info/namespace_packages.txt
src/crl.examplelib.egg-info/top_level.txt
src/crl/examplelib/__init__.py
src/crl/examplelib/_version.py
src/crl/examplelib/examplelib.py
src/crl/examplelib/examplelib_implementation.py
src/crl/examplelib/robotdocsconf.py
tests/__init__.py
tests/test_examplelib.py