Metadata-Version: 1.1
Name: crl.examplelib
Version: 1.1.3
Summary: Example of Common Robot Library
Home-page: https://github.com/nokia/crl-examplelib
Author: Petri Huovinen
Author-email: petri.huovinen@nokia.com
License: BSD-3-Clause
Keywords: robotframework,example
Platform: UNKNOWN
Classifier: Intended Audience :: Developers
Classifier: License :: OSI Approved :: BSD License
Classifier: Programming Language :: Python :: 2
Classifier: Programming Language :: Python :: 3
Classifier: Topic :: Software Development
